MANIFEST.in
README
__init__.py
__pkginfo__.py
entities.py
hooks.py
schema.py
setup.py
tmp.py
views.py
cubicweb_tagsinput.egg-info/PKG-INFO
cubicweb_tagsinput.egg-info/SOURCES.txt
cubicweb_tagsinput.egg-info/dependency_links.txt
cubicweb_tagsinput.egg-info/not-zip-safe
cubicweb_tagsinput.egg-info/requires.txt
cubicweb_tagsinput.egg-info/top_level.txt
data/bootstrap-tagsinput-angular.js
data/bootstrap-tagsinput.css
data/bootstrap-tagsinput.js
data/bootstrap-tagsinput.min.js
data/typeahead.bundle.js
i18n/en.po
i18n/es.po
i18n/fr.po
migration/postcreate.py
test/pytestconf.py
test/test_tagsinput.py