Metadata-Version: 1.1
Name: cubicweb-tagsinput
Version: 0.2.4
Summary: Provides https://github.com/timschlechter/bootstrap-tagsinput based widgets
Home-page: http://www.cubicweb.org/project/cubicweb-tagsinput
Author: UNLISH S.A.S. (Montpellier, FRANCE)
Author-email: contact@unlish.com
License: LGPL
Platform: UNKNOWN
Classifier: Environment :: Web Environment
Classifier: Framework :: CubicWeb
Classifier: Programming Language :: Python
Classifier: Programming Language :: JavaScript
